napari_yolov5/__init__.py
napari_yolov5/_dock_widget.py
napari_yolov5/_function.py
napari_yolov5/val.py
napari_yolov5/yolov5s.pt
napari_yolov5/_tests/__init__.py
napari_yolov5/_tests/detect-napari.py
napari_yolov5/_tests/test_dock_widget.py
napari_yolov5/_tests/test_function.py
napari_yolov5/_tests/train-napari - Copy.py
napari_yolov5/_tests/train-napari.py
napari_yolov5/_tests/train-test.py
napari_yolov5/data/Argoverse.yaml
napari_yolov5/data/GlobalWheat2020.yaml
napari_yolov5/data/Objects365.yaml
napari_yolov5/data/SKU-110K.yaml
napari_yolov5/data/VOC.yaml
napari_yolov5/data/VisDrone.yaml
napari_yolov5/data/__init__.py
napari_yolov5/data/coco.yaml
napari_yolov5/data/coco128.yaml
napari_yolov5/data/xView.yaml
napari_yolov5/data/hyps/hyp.finetune.yaml
napari_yolov5/data/hyps/hyp.finetune_objects365.yaml
napari_yolov5/data/hyps/hyp.scratch-high.yaml
napari_yolov5/data/hyps/hyp.scratch-low.yaml
napari_yolov5/data/hyps/hyp.scratch-med.yaml
napari_yolov5/data/hyps/hyp.scratch.yaml
napari_yolov5/data/scripts/download_weights.sh
napari_yolov5/data/scripts/get_coco.sh
napari_yolov5/data/scripts/get_coco128.sh
napari_yolov5/models/__init__.py
napari_yolov5/models/common.py
napari_yolov5/models/experimental.py
napari_yolov5/models/tf.py
napari_yolov5/models/yolo.py
napari_yolov5/models/yolov5l.yaml
napari_yolov5/models/yolov5m.yaml
napari_yolov5/models/yolov5n.yaml
napari_yolov5/models/yolov5s.yaml
napari_yolov5/models/yolov5x.yaml
napari_yolov5/models/hub/anchors.yaml
napari_yolov5/models/hub/yolov3-spp.yaml
napari_yolov5/models/hub/yolov3-tiny.yaml
napari_yolov5/models/hub/yolov3.yaml
napari_yolov5/models/hub/yolov5-bifpn.yaml
napari_yolov5/models/hub/yolov5-fpn.yaml
napari_yolov5/models/hub/yolov5-p2.yaml
napari_yolov5/models/hub/yolov5-p6.yaml
napari_yolov5/models/hub/yolov5-p7.yaml
napari_yolov5/models/hub/yolov5-panet.yaml
napari_yolov5/models/hub/yolov5l6.yaml
napari_yolov5/models/hub/yolov5m6.yaml
napari_yolov5/models/hub/yolov5n6.yaml
napari_yolov5-0.2.11.dist-info/LICENSE
napari_yolov5-0.2.11.dist-info/METADATA
napari_yolov5-0.2.11.dist-info/WHEEL
napari_yolov5-0.2.11.dist-info/entry_points.txt
napari_yolov5-0.2.11.dist-info/top_level.txt
napari_yolov5-0.2.11.dist-info/RECORD
