Metadata-Version: 2.1
Name: napari-yolov5
Version: 0.2.11
Summary: Plugin adapted from Ultralytics to bring YOLOv5 into Napari
Home-page: https://github.com/rdemets/napari-yolov5
Author: Richard De Mets
Author-email: demets.richard@gmail.com
License: GPL-3.0-only
Platform: UNKNOWN
Classifier: Development Status :: 2 - Pre-Alpha
Classifier: Intended Audience :: Developers
Classifier: Framework :: napari
Classifier: Topic :: Software Development :: Testing
Classifier: Programming Language :: Python
Classifier: Programming Language :: Python :: 3
Classifier: Programming Language :: Python :: 3.7
Classifier: Programming Language :: Python :: 3.8
Classifier: Programming Language :: Python :: 3.9
Classifier: Operating System :: OS Independent
Classifier: License :: OSI Approved :: GNU General Public License v3 (GPLv3)
Requires-Python: >=3.7
License-File: LICENSE
Requires-Dist: napari-plugin-engine (>=0.1.4)
Requires-Dist: matplotlib (>=3.2.2)
Requires-Dist: numpy (>=1.18.5)
Requires-Dist: opencv-python (>=4.1.2)
Requires-Dist: Pillow (>=7.1.2)
Requires-Dist: PyYAML (>=5.3.1)
Requires-Dist: requests (>=2.23.0)
Requires-Dist: scipy (>=1.4.1)
Requires-Dist: torch (>=1.9.0)
Requires-Dist: tqdm (>=4.41.0)
Requires-Dist: seaborn (>=0.11.2)
Requires-Dist: tensorboard (>=1.15.0)
Requires-Dist: connected-components-3d (>=3.6.0)
Requires-Dist: torchvision (>=0.8.1)
